openapiart/__init__.py
openapiart/bundler.py
openapiart/common.go
openapiart/common.py
openapiart/common_test.go
openapiart/generator.py
openapiart/gotidy.py
openapiart/loggers.go
openapiart/openapiart.py
openapiart/openapiartgo.py
openapiart/openapiartplugin.py
openapiart/openapiartprotobuf.py
openapiart/openapiartpython.py
openapiart/requirements.py
openapiart/requirements.txt
openapiart/telemetry.go
openapiart/test_requirements.txt
openapiart/goserver/__init__.py
openapiart/goserver/generator_context.py
openapiart/goserver/go_controller_generator.py
openapiart/goserver/go_interface_generator.py
openapiart/goserver/goserver.py
openapiart/goserver/http_setup.go
openapiart/goserver/response.go
openapiart/goserver/string_util.py
openapiart/goserver/writer.py
openapiart/goserver/api/api.yaml
openapiart/goserver/api/common.yaml
openapiart/goserver/api/service_a.api.yaml
openapiart/goserver/api/service_a.yaml
openapiart/goserver/api/service_b.api.yaml
openapiart/goserver/api/service_b.yaml
openapiart/tests/__init__.py
openapiart/tests/conftest.py
openapiart/tests/grpcserver.py
openapiart/tests/server.py
openapiart/tests/test_add.py
openapiart/tests/test_auto.py
openapiart/tests/test_bundle.py
openapiart/tests/test_bundler.py
openapiart/tests/test_choice.py
openapiart/tests/test_constraints.py
openapiart/tests/test_enum_validation.py
openapiart/tests/test_error_schema.py
openapiart/tests/test_fielduid.py
openapiart/tests/test_formats.py
openapiart/tests/test_func.py
openapiart/tests/test_grpc_response.py
openapiart/tests/test_http_response.py
openapiart/tests/test_integer_format.py
openapiart/tests/test_license.py
openapiart/tests/test_oid_format.py
openapiart/tests/test_perf.py
openapiart/tests/test_protobuf.py
openapiart/tests/test_py_go_diff.py
openapiart/tests/test_random_pattern.py
openapiart/tests/test_remove.py
openapiart/tests/test_required_choices.py
openapiart/tests/test_secure_grpc_response.py
openapiart/tests/test_set.py
openapiart/tests/test_unique.py
openapiart-0.3.38.dist-info/licenses/LICENSE
openapiart-0.3.38.dist-info/METADATA
openapiart-0.3.38.dist-info/WHEEL
openapiart-0.3.38.dist-info/top_level.txt
openapiart-0.3.38.dist-info/RECORD
