Metadata-Version: 2.4
Name: openapiart
Version: 0.3.38
Summary: The OpenAPI Artifact Generator Python Package
Author-email: Keysight Technologies <andy.balogh@keysight.com>
License-Expression: MIT
Project-URL: Repository, https://github.com/open-traffic-generator/openapiart
Keywords: testing,openapi,artifact,generator
Classifier: Development Status :: 5 - Production/Stable
Classifier: Intended Audience :: Developers
Classifier: Topic :: Software Development :: Testing :: Traffic Generation
Classifier: Programming Language :: Python :: 3
Classifier: Programming Language :: Python :: 3.8
Classifier: Programming Language :: Python :: 3.9
Classifier: Programming Language :: Python :: 3.10
Classifier: Programming Language :: Python :: 3.11
Classifier: Programming Language :: Python :: 3.12
Requires-Python: <4,>=3.8
License-File: LICENSE
Requires-Dist: build
Requires-Dist: jsonpath-ng
Requires-Dist: typing
Requires-Dist: setuptools
Requires-Dist: wheel
Requires-Dist: PyYAML
Requires-Dist: openapi_spec_validator==0.3.0
Requires-Dist: requests
Requires-Dist: typing_extensions
Requires-Dist: click==8.1.7
Requires-Dist: black==22.3.0
Requires-Dist: grpcio-tools~=1.70.0
Requires-Dist: pipreqs==0.4.11
Requires-Dist: protobuf~=5.29.5
Requires-Dist: grpcio~=1.70.0
Provides-Extra: testing
Requires-Dist: twine; extra == "testing"
Requires-Dist: flask; python_version <= "3.6" and extra == "testing"
Requires-Dist: flask==2.2.5; python_version > "3.6" and extra == "testing"
Requires-Dist: pytest; extra == "testing"
Requires-Dist: flake8; extra == "testing"
Requires-Dist: pytest-cov; extra == "testing"
Requires-Dist: jsonpath_ng; extra == "testing"
Requires-Dist: urllib3; extra == "testing"
Requires-Dist: semantic_version; extra == "testing"
Dynamic: license-file
